[
  {
    "movement_id": "842168d1-2da5-45bf-bc97-91488064e8d8",
    "product_id": "PRD-42532f88",
    "movement_type": "SALE",
    "quantity": -5,
    "reference_id": "INV-20260227130529",
    "created_at": "2026-02-27T13:06:59.403531",
    "notes": ""
  },
  {
    "movement_id": "0d31b326-9c17-4d3f-8be1-59c46b1fe21c",
    "product_id": "PRD-d6d85753",
    "movement_type": "SALE",
    "quantity": -10,
    "reference_id": "INV-20260227130529",
    "created_at": "2026-02-27T13:06:59.414096",
    "notes": ""
  },
  {
    "movement_id": "4497b0b2-c127-45aa-af5e-092d8e234f92",
    "product_id": "PRD-21085f71",
    "movement_type": "SALE",
    "quantity": -10,
    "reference_id": "INV-20260227130529",
    "created_at": "2026-02-27T13:06:59.429888",
    "notes": ""
  },
  {
    "movement_id": "cefe400c-528f-4766-b1fc-39ddc4a2879a",
    "product_id": "PRD-d6d85753",
    "movement_type": "SALE",
    "quantity": -1,
    "reference_id": "INV-20260227130702",
    "created_at": "2026-02-27T13:09:06.249922",
    "notes": ""
  },
  {
    "movement_id": "330305c9-3136-4f1f-af7a-5bb9949a959f",
    "product_id": "PRD-42532f88",
    "movement_type": "SALE",
    "quantity": -1,
    "reference_id": "INV-20260227130702",
    "created_at": "2026-02-27T13:09:06.270725",
    "notes": ""
  },
  {
    "movement_id": "c12ba6c1-37b7-4843-87c7-429f1fa4e4d9",
    "product_id": "PRD-21085f71",
    "movement_type": "SALE",
    "quantity": -1,
    "reference_id": "INV-20260227130702",
    "created_at": "2026-02-27T13:09:06.286225",
    "notes": ""
  }
]